<config>
  <event_variant class="MousePressEvent" name="AddingAddition">
    <attribute name="EventButton" value="LeftMouseButton"/>
  </event_variant>
  <event_variant class="MouseReleaseEvent" name="AddingAddition">
    <attribute name="EventButton" value="LeftMouseButton"/>
  </event_variant>
  <event_variant class="MouseMoveEvent" name="AddingAddition">
    <attribute name="ButtonState" value="LeftMouseButton"/>
  </event_variant>
  <event_variant class="MousePressEvent" name="AddingSubtraction">
    <attribute name="EventButton" value="MiddleMouseButton"/>
  </event_variant>
  <event_variant class="MouseReleaseEvent" name="AddingSubtraction">
    <attribute name="EventButton" value="MiddleMouseButton"/>
  </event_variant>
  <event_variant class="MouseMoveEvent" name="AddingSubtraction">
    <attribute name="ButtonState" value="MiddleMouseButton"/>
  </event_variant>
  <event_variant class="MousePressEvent" name="RemovingSubtraction">
    <attribute name="EventButton" value="RightMouseButton"/>
  </event_variant>
   <event_variant class="MouseMoveEvent" name="RemovingSubtraction">
    <attribute name="ButtonState" value="RightMouseButton"/>
  </event_variant>
  <event_variant class="MouseReleaseEvent" name="RemovingSubtraction">
    <attribute name="EventButton" value="RightMouseButton"/>
  </event_variant>
</config>
